Metadata-Version: 2.1
Name: wordcloud-lite
Version: 1.3
Summary: Generate Word Cloud with ease.
Home-page: https://github.com/sonucr7/wordcloud_lite
Author: Sonu Kumar
Author-email: sonu1000raw@gmail.com
License: MIT
Download-URL: https://github.com/sonucr7/wordcloud_lite/archive/v_01.tar.gz
Keywords: WordCloud,NLP
Platform: UNKNOWN
Classifier: Development Status :: 3 - Alpha
Classifier: Intended Audience :: Developers
Classifier: Topic :: Software Development :: Build Tools
Classifier: License :: OSI Approved :: MIT License
Classifier: Programming Language :: Python :: 3
Classifier: Programming Language :: Python :: 3.4
Classifier: Programming Language :: Python :: 3.5
Classifier: Programming Language :: Python :: 3.6
Classifier: Programming Language :: Python :: 3.8
